serial_to_parallel.v
module serial_to_parallel (
    input clk,
    input reset,
    input serial_in,
    input load,
    output reg [31:0] parallel_out
);
    reg [31:0] shift_reg; // Shift register to store serial data

    always @(posedge clk or posedge reset) begin
        if (reset) begin
            shift_reg <= 32'b0; // Reset the shift register
            parallel_out <= 32'b0; // Reset the parallel output
        end else if (load) begin
            parallel_out <= shift_reg; // Load the shift register into parallel_out
        end else begin
            shift_reg <= {shift_reg[30:0], serial_in}; // Shift in serial data
        end
    end
endmodule

tb_serial_to_parallel.v
module tb_serial_to_parallel;
    reg clk;
    reg reset;
    reg serial_in;
    reg load;
    wire [31:0] parallel_out;

    // Instantiate the design under test (DUT)
    serial_to_parallel dut (
        .clk(clk),
        .reset(reset),
        .serial_in(serial_in),
        .load(load),
        .parallel_out(parallel_out)
    );

    // Clock generation
    always #5 clk = ~clk; // Toggle clock every 5 time units

    // Stimulus
    initial begin
        $dumpfile("dump.vcd"); // Specifies the VCD file name
        $dumpvars(0, tb_serial_to_parallel); // Dumps all variables in testbench

        // Initialize signals
        clk = 0;
        reset = 0;
        serial_in = 0;
        load = 0;

        // Apply reset
        reset = 1;
        #10 reset = 0;

        // Send serial data (example: 1101 in binary)
        serial_in = 1; #10;
        serial_in = 1; #10;
        serial_in = 1; #10;
        serial_in = 0; #10;

        // Continue sending remaining 28 bits
        repeat (28) begin
            serial_in = $random % 2; // Random 0 or 1
            #10;
        end

        // Load the shifted data into the parallel output
        load = 1;
        #10 load = 0;

        // Monitor parallel output
        $monitor("Time=%0t | parallel_out=%b", $time, parallel_out);

        // Wait for some time before finishing simulation
        #50; $finish;
    end
endmodule

dump.vcd
$date
	Thu Mar 20 13:23:22 2025
$end
$version
	Icarus Verilog
$end
$timescale
	1s
$end
$scope module tb_serial_to_parallel $end
$var wire 32 ! parallel_out [31:0] $end
$var reg 1 " clk $end
$var reg 1 # load $end
$var reg 1 $ reset $end
$var reg 1 % serial_in $end
$scope module dut $end
$var wire 1 " clk $end
$var wire 1 # load $end
$var wire 1 $ reset $end
$var wire 1 % serial_in $end
$var reg 32 & parallel_out [31:0] $end
$var reg 32 ' shift_reg [31:0] $end
$upscope $end
$upscope $end
$enddefinitions $end
#0
$dumpvars
b0 '
bx &
0%
1$
0#
0"
bx !
$end
#5
1"
#10
0"
1%
0$
#15
b1 '
1"
#20
0"
#25
b11 '
1"
#30
0"
#35
b111 '
1"
#40
0"
0%
#45
b1110 '
1"
#50
0"
#55
b11100 '
1"
#60
0"
1%
#65
b111001 '
1"
#70
0"
#75
b1110011 '
1"
#80
0"
#85
b11100111 '
1"
#90
0"
#95
b111001111 '
1"
#100
0"
#105
b1110011111 '
1"
#110
0"
#115
b11100111111 '
1"
#120
0"
0%
#125
b111001111110 '
1"
#130
0"
1%
#135
b1110011111101 '
1"
#140
0"
#145
b11100111111011 '
1"
#150
0"
0%
#155
b111001111110110 '
1"
#160
0"
1%
#165
b1110011111101101 '
1"
#170
0"
#175
b11100111111011011 '
1"
#180
0"
0%
#185
b111001111110110110 '
1"
#190
0"
1%
#195
b1110011111101101101 '
1"
#200
0"
0%
#205
b11100111111011011010 '
1"
#210
0"
1%
#215
b111001111110110110101 '
1"
#220
0"
0%
#225
b1110011111101101101010 '
1"
#230
0"
1%
#235
b11100111111011011010101 '
1"
#240
0"
#245
b111001111110110110101011 '
1"
#250
0"
0%
#255
b1110011111101101101010110 '
1"
#260
0"
1%
#265
b11100111111011011010101101 '
1"
#270
0"
0%
#275
b111001111110110110101011010 '
1"
#280
0"
#285
b1110011111101101101010110100 '
1"
#290
0"
#295
b11100111111011011010101101000 '
1"
#300
0"
1%
#305
b111001111110110110101011010001 '
1"
#310
0"
0%
#315
b1110011111101101101010110100010 '
1"
#320
0"
1%
#325
b11100111111011011010101101000101 '
1"
#330
0"
1#
#335
b11100111111011011010101101000101 !
b11100111111011011010101101000101 &
b11001111110110110101011010001011 '
1"
#340
0"
0#
#345
b10011111101101101010110100010111 '
1"
#350
0"
#355
b111111011011010101101000101111 '
1"
#360
0"
#365
b1111110110110101011010001011111 '
1"
#370
0"
#375
b11111101101101010110100010111111 '
1"
#380
0"
#385
b11111011011010101101000101111111 '
1"
